plugml
