Metadata-Version: 1.0
Name: plugml
Version: 0.2.1
Summary: easy-to-use and highly modular machine learning framework
Home-page: https://github.com/mkraemer67/plugml
Author: Martin Krämer
Author-email: mkraemer.de@gmail.com
License: Apache
Platform: UNKNOWN
